porthound/__init__.py
porthound/porthound.py
porthound-0.1.0.dist-info/LICENSE
porthound-0.1.0.dist-info/METADATA
porthound-0.1.0.dist-info/WHEEL
porthound-0.1.0.dist-info/entry_points.txt
porthound-0.1.0.dist-info/top_level.txt
porthound-0.1.0.dist-info/RECORD
